ansible_base/__init__.py
ansible_base/activitystream/__init__.py
ansible_base/activitystream/admin.py
ansible_base/activitystream/apps.py
ansible_base/activitystream/filtering.py
ansible_base/activitystream/serializers.py
ansible_base/activitystream/signals.py
ansible_base/activitystream/urls.py
ansible_base/activitystream/views.py
ansible_base/activitystream/migrations/0001_initial.py
ansible_base/activitystream/migrations/0002_alter_entry_created_by.py
ansible_base/activitystream/migrations/0003_alter_entry_options.py
ansible_base/activitystream/migrations/0004_alter_entry_created_alter_entry_created_by.py
ansible_base/activitystream/migrations/0005_alter_entry_changes_alter_entry_content_type_and_more.py
ansible_base/activitystream/migrations/__init__.py
ansible_base/activitystream/models/__init__.py
ansible_base/activitystream/models/entry.py
ansible_base/api_documentation/__init__.py
ansible_base/api_documentation/apps.py
ansible_base/api_documentation/customizations.py
ansible_base/api_documentation/filter_extensions.py
ansible_base/api_documentation/postprocessing_hooks.py
ansible_base/api_documentation/preprocessing_hooks.py
ansible_base/api_documentation/urls.py
ansible_base/api_documentation/migrations/__init__.py
ansible_base/authentication/__init__.py
ansible_base/authentication/admin.py
ansible_base/authentication/apps.py
ansible_base/authentication/backend.py
ansible_base/authentication/middleware.py
ansible_base/authentication/session.py
ansible_base/authentication/social_auth.py
ansible_base/authentication/urls.py
ansible_base/authentication/authenticator_configurators/__init__.py
ansible_base/authentication/authenticator_configurators/github.py
ansible_base/authentication/authenticator_plugins/__init__.py
ansible_base/authentication/authenticator_plugins/_radiusauth.py
ansible_base/authentication/authenticator_plugins/azuread.py
ansible_base/authentication/authenticator_plugins/base.py
ansible_base/authentication/authenticator_plugins/github.py
django_ansible_base-2026.1.26.dist-info/licenses/LICENSE
django_ansible_base-2026.1.26.dist-info/METADATA
django_ansible_base-2026.1.26.dist-info/WHEEL
django_ansible_base-2026.1.26.dist-info/top_level.txt
django_ansible_base-2026.1.26.dist-info/RECORD
