Metadata-Version: 2.4
Name: django-ansible-base
Version: 2026.1.26
Summary: A Django app used by ansible services
Author-email: "Red Hat, Inc." <info@ansible.com>, John Westcott IV <john.westcott.iv@redhat.com>
License: Apache-2.0
Project-URL: Repository, https://github.com/ansible/django-ansible-base
Keywords: ansible,django
Classifier: Framework :: Django
Classifier: Development Status :: 5 - Production/Stable
Classifier: Environment :: Web Environment
Classifier: Framework :: Django
Classifier: Intended Audience :: Developers
Classifier: Intended Audience :: System Administrators
Classifier: Operating System :: OS Independent
Classifier: License :: OSI Approved :: Apache Software License
Classifier: Programming Language :: Python
Classifier: Programming Language :: Python :: 3
Classifier: Programming Language :: Python :: 3.11
Classifier: Programming Language :: Python :: 3.12
Requires-Python: >=3.11
License-File: LICENSE
Requires-Dist: cryptography
Requires-Dist: Django<6.0,>=4.2.26
Requires-Dist: djangorestframework<3.16
Requires-Dist: django-crum
Requires-Dist: inflection
Requires-Dist: sqlparse>=0.5.2
Requires-Dist: dynaconf<4.0.0,>=3.2.10
Provides-Extra: all
Requires-Dist: social-auth-app-django==5.4.1; extra == "all"
Requires-Dist: social-auth-core<=4.5.4; extra == "all"
Requires-Dist: tabulate; extra == "all"
Requires-Dist: django-auth-ldap; extra == "all"
Requires-Dist: python-ldap; extra == "all"
Requires-Dist: ldap-filter; extra == "all"
Requires-Dist: python3-saml; extra == "all"
Requires-Dist: tacacs_plus; extra == "all"
Requires-Dist: xmlsec==1.3.13; extra == "all"
Requires-Dist: lxml==5.3.0; extra == "all"
Requires-Dist: pyrad; extra == "all"
Requires-Dist: drf-spectacular<1.0; extra == "all"
Requires-Dist: referencing<0.37.0; extra == "all"
Requires-Dist: channels; extra == "all"
Requires-Dist: pyjwt; extra == "all"
Requires-Dist: requests; extra == "all"
Requires-Dist: cryptography; extra == "all"
Requires-Dist: pytest; extra == "all"
Requires-Dist: pytest-django; extra == "all"
Requires-Dist: django-redis; extra == "all"
Requires-Dist: redis; extra == "all"
Requires-Dist: django-oauth-toolkit<2.4.0; extra == "all"
Requires-Dist: asgiref; extra == "all"
Requires-Dist: pyjwt; extra == "all"
Requires-Dist: requests; extra == "all"
Requires-Dist: urllib3; extra == "all"
Requires-Dist: django-flags; extra == "all"
Provides-Extra: activitystream
Provides-Extra: authentication
Requires-Dist: social-auth-app-django==5.4.1; extra == "authentication"
Requires-Dist: social-auth-core<=4.5.4; extra == "authentication"
Requires-Dist: tabulate; extra == "authentication"
Requires-Dist: django-auth-ldap; extra == "authentication"
Requires-Dist: python-ldap; extra == "authentication"
Requires-Dist: ldap-filter; extra == "authentication"
Requires-Dist: python3-saml; extra == "authentication"
Requires-Dist: tacacs_plus; extra == "authentication"
Requires-Dist: xmlsec==1.3.13; extra == "authentication"
Requires-Dist: lxml==5.3.0; extra == "authentication"
Requires-Dist: pyrad; extra == "authentication"
Provides-Extra: api-documentation
Requires-Dist: drf-spectacular<1.0; extra == "api-documentation"
Requires-Dist: referencing<0.37.0; extra == "api-documentation"
Provides-Extra: rest-filters
Provides-Extra: rbac
Provides-Extra: channel-auth
Requires-Dist: channels; extra == "channel-auth"
Provides-Extra: jwt-consumer
Requires-Dist: pyjwt; extra == "jwt-consumer"
Requires-Dist: requests; extra == "jwt-consumer"
Provides-Extra: testing
Requires-Dist: cryptography; extra == "testing"
Requires-Dist: pytest; extra == "testing"
Requires-Dist: pytest-django; extra == "testing"
Provides-Extra: redis-client
Requires-Dist: django-redis; extra == "redis-client"
Requires-Dist: redis; extra == "redis-client"
Provides-Extra: oauth2-provider
Requires-Dist: django-oauth-toolkit<2.4.0; extra == "oauth2-provider"
Provides-Extra: resource-registry
Requires-Dist: asgiref; extra == "resource-registry"
Requires-Dist: pyjwt; extra == "resource-registry"
Requires-Dist: requests; extra == "resource-registry"
Requires-Dist: urllib3; extra == "resource-registry"
Provides-Extra: feature-flags
Requires-Dist: django-flags; extra == "feature-flags"
Dynamic: license-file
